mhar/__init__.py
mhar/_modidx.py
mhar/core.py
mhar/inner_point.py
mhar/polytope.py
mhar/polytope_examples.py
mhar/utils.py
mhar/walk.py
mhar/warningss.py
mhar-1.0.4.dist-info/LICENSE
mhar-1.0.4.dist-info/METADATA
mhar-1.0.4.dist-info/WHEEL
mhar-1.0.4.dist-info/entry_points.txt
mhar-1.0.4.dist-info/top_level.txt
mhar-1.0.4.dist-info/RECORD
